confidant/__init__.py
confidant/app.py
confidant/encrypted_settings.py
confidant/settings.py
confidant/wsgi.py
confidant/authnz/__init__.py
confidant/authnz/errors.py
confidant/authnz/rbac.py
confidant/authnz/userauth.py
confidant/clients/__init__.py
confidant/lib/__init__.py
confidant/lib/cryptolib.py
confidant/models/__init__.py
confidant/models/blind_credential.py
confidant/models/credential.py
confidant/models/non_null_unicode_set_attribute.py
confidant/models/service.py
confidant/routes/__init__.py
confidant/routes/blind_credentials.py
confidant/routes/certificates.py
confidant/routes/credentials.py
confidant/routes/identity.py
confidant/routes/jwks.py
confidant/routes/saml.py
confidant/routes/services.py
confidant/routes/static_files.py
confidant/schema/__init__.py
confidant/schema/auto_build_schema.py
confidant/schema/blind_credentials.py
confidant/schema/certificates.py
confidant/schema/credentials.py
confidant/schema/jwks.py
confidant/schema/services.py
confidant/scripts/__init__.py
confidant/scripts/archive.py
confidant/scripts/bootstrap.py
confidant/scripts/manage.py
confidant/scripts/migrate.py
confidant/scripts/migrate_bool.py
confidant/scripts/restore.py
confidant/scripts/utils.py
confidant/services/__init__.py
confidant/services/certificatemanager.py
confidant/services/ciphermanager.py
confidant/services/credentialmanager.py
confidant/services/graphite.py
confidant/services/iamrolemanager.py
confidant/services/jwkmanager.py
confidant/services/keymanager.py
confidant/services/servicemanager.py
confidant/services/webhook.py
confidant/utils/__init__.py
confidant/utils/dynamodb.py
confidant/utils/maintenance.py
confidant/utils/misc.py
confidant-6.6.1.dist-info/LICENSE
confidant-6.6.1.dist-info/METADATA
confidant-6.6.1.dist-info/NOTICE
confidant-6.6.1.dist-info/WHEEL
confidant-6.6.1.dist-info/entry_points.txt
confidant-6.6.1.dist-info/top_level.txt
confidant-6.6.1.dist-info/RECORD
